Metadata-Version: 2.4
Name: coc.py
Version: 4.0.0
Summary: A python wrapper for the Clash of Clans API
Author: mathsman5133
Maintainer: majordoobie, MagicTheDev, Kuchenmampfer, lukasthaler, doluk
License: MIT
Project-URL: documentation, https://cocpy.readthedocs.io/en/latest/
Project-URL: repository, https://github.com/mathsman5133/coc.py
Project-URL: changelog, https://cocpy.readthedocs.io/en/latest/miscellaneous/changelog.html
Keywords: coc,clash of clans,coc.py,clash api
Classifier: Development Status :: 5 - Production/Stable
Classifier: Programming Language :: Python
Classifier: Natural Language :: English
Classifier: Operating System :: OS Independent
Requires-Python: >=3.10.0
License-File: LICENSE
Requires-Dist: aiohttp
Requires-Dist: orjson
Provides-Extra: docs
Requires-Dist: sphinx; extra == "docs"
Requires-Dist: sphinx_rtd_theme; extra == "docs"
Requires-Dist: sphinxcontrib_trio; extra == "docs"
Requires-Dist: autodocsumm; extra == "docs"
Dynamic: license-file
